billboard/__init__.py
billboard/album/__init__.py
billboard/album/album.py
billboard/artists/__init__.py
billboard/artists/artist.py
billboard/songs/__init__.py
billboard/songs/glob.py
billboard/songs/hot.py
billboard/songs/song_charts.py
billboard/songs/super.py
billboard/super.py
billboard/utils/__init__.py
billboard/utils/dataclasses/__init__.py
billboard/utils/dataclasses/entry.py
billboard/utils/dataclasses/titled_entry.py
billboard/utils/funcs.py
billboard-0.4.0.dist-info/LICENSE
billboard-0.4.0.dist-info/METADATA
billboard-0.4.0.dist-info/WHEEL
billboard-0.4.0.dist-info/RECORD
